bipolarizer/__init__.py
bipolarizer/bipolarizer.py
bipolarizer-1.0a1.dist-info/LICENSE
bipolarizer-1.0a1.dist-info/METADATA
bipolarizer-1.0a1.dist-info/WHEEL
bipolarizer-1.0a1.dist-info/top_level.txt
bipolarizer-1.0a1.dist-info/RECORD
