Metadata-Version: 2.1
Name: bipolarizer
Version: 1.0a1
Summary: Simple bipolarizer for images
Home-page: https://github.com/JeanMaximilienCadic
Author: Jean Maximilien Cadic
Author-email: j.cadic@pm.me
License: MIT
Platform: UNKNOWN
Classifier: Programming Language :: Python :: 3.6
Classifier: License :: OSI Approved :: MIT License
Requires-Python: >=3.6
Requires-Dist: opencv-python
Requires-Dist: numpy
